<Properties StartupConfiguration="{A30AE1FE-D6E6-49C0-AD06-0E4AE4E3B1A2}|Default">
  <MultiItemStartupConfigurations />
  <MonoDevelop.Ide.Workspace ActiveConfiguration="Debug" />
  <MonoDevelop.Ide.DebuggingService.PinnedWatches />
  <MonoDevelop.Ide.ItemProperties.Taskmanager PreferredExecutionTarget="/Applications/Google Chrome.app" />
  <MonoDevelop.Ide.DebuggingService.Breakpoints>
    <BreakpointStore />
  </MonoDevelop.Ide.DebuggingService.Breakpoints>
  <MonoDevelop.Ide.Workbench ActiveDocument="Taskmanager/Controllers/TodoController.cs">
    <Files>
      <File FileName="Taskmanager/Controllers/TodoController.cs" Line="46" Column="1" />
      <File FileName="Taskmanager/Views/Todo/Index.cshtml" Line="22" Column="35" />
      <File FileName="Taskmanager/Views/Todo/Create.cshtml" Line="1" Column="62" />
      <File FileName="Taskmanager/Properties/launchSettings.json" Line="15" Column="48" />
      <File FileName="Taskmanager/Program.cs" Line="27" Column="1" />
    </Files>
    <Pads>
      <Pad Id="ProjectPad">
        <State name="__root__">
          <Node name="Taskmanager" expanded="True">
            <Node name="Taskmanager" expanded="True">
              <Node name="Controllers" expanded="True">
                <Node name="TodoController.cs" selected="True" />
              </Node>
              <Node name="Models" expanded="True" />
              <Node name="Properties" expanded="True" />
              <Node name="Views" expanded="True">
                <Node name="Home" expanded="True" />
                <Node name="Shared" expanded="True" />
                <Node name="Todo" expanded="True" />
              </Node>
              <Node name="appsettings.json" expanded="True" />
            </Node>
          </Node>
        </State>
      </Pad>
      <Pad Id="MonoDevelop.Debugger.WatchPad">
        <State />
      </Pad>
    </Pads>
  </MonoDevelop.Ide.Workbench>
</Properties>